[
    {
        "link_text":"Visit Google",
        "link_source":"https://www.google.com",
        "Slug": "Visit Google",
        "ISO2": "Visit Google"
    },
    {
        "link_text":"Visit Google",
        "link_source":"https://www.youtube.com",
        "Slug": "Visit Google",
        "ISO2": "Visit Google"
    },
    {
        "link_text":"Visit Google",
        "link_source":"https://download1327.mediafire.com/tyy6ng6v9b7gdJthYxGzxzDbh4MlzsOPdb_ht0OGVeaWdyDKeHjNAKQgB88a8L4De-zxFVTlMzqBUDRH78ym7e39Oca3V28sujW-at8TJoItDABXXFb1pN59ezXBCb7JGkJx7sfr2jz113ifwm4tdcINlmp_uQZstXVqQAGjMJA/slfahqj5ao82d9j/%5BDownloadgameps3.com%5D-Alone.With.You.PS4-CUSA04792.pkg",
        "Slug": "Visit Google",
        "ISO2": "Visit Google"
    },
]
